{"width":512,"imagePath":"enemyfinalsetup3_tex.png","height":256,"name":"enemyfinalsetup3","SubTexture":[{"width":46,"y":196,"height":43,"name":"tangan_kiri","x":49},{"width":46,"y":196,"height":43,"name":"tangan_kanan","x":1},{"width":191,"y":1,"height":193,"name":"enemy_3","x":1},{"width":134,"y":1,"height":149,"name":"aksesoris","x":194},{"width":29,"y":196,"height":26,"name":"perangkap_1","x":126},{"width":31,"y":228,"height":25,"name":"perangkap_2","x":130},{"width":22,"y":196,"height":29,"name":"perangkap_3","x":157},{"width":27,"y":196,"height":30,"name":"perangkap_4","x":97},{"width":31,"y":228,"height":25,"name":"perangkap_5","x":97}]}